LICENSE
MANIFEST.in
README.md
setup.py
tailow/__init__.py
tailow/connection.py
tailow/document.py
tailow/queryset.py
tailow.egg-info/PKG-INFO
tailow.egg-info/SOURCES.txt
tailow.egg-info/dependency_links.txt
tailow.egg-info/requires.txt
tailow.egg-info/top_level.txt
tailow/fields/__init__.py
tailow/fields/base.py
tailow/fields/datetime.py
tailow/fields/integer.py
tailow/fields/list.py
tailow/fields/reference.py
tailow/fields/string.py
tailow/operators/__init__.py
tailow/operators/base.py
tailow/operators/inopr.py