Metadata-Version: 1.0
Name: tailow
Version: 0.1.0
Summary: A async wrapper for mongodb
Home-page: https://github.com/sourcepirate/tailow.git
Author: Sourcepirate
Author-email: sathyanarrayanan@yandex.com
License: UNKNOWN
Platform: UNKNOWN
